console/__init__.py
console/console.py
fastauth_client-0.1.0.dist-info/LICENCE
fastauth_client-0.1.0.dist-info/METADATA
fastauth_client-0.1.0.dist-info/WHEEL
fastauth_client-0.1.0.dist-info/top_level.txt
fastauth_client-0.1.0.dist-info/RECORD
