Metadata-Version: 2.1
Name: fastauth-client
Version: 0.1.0
Summary: A utility for printing colored messages to the console.
Home-page: https://github.com/sikandar1838/console
Author: Sikandar Moyal
Author-email: sikandar1838@gmail.com
License: MIT
Keywords: Console,Colorful Output,CLI,Text Formatting
Classifier: Programming Language :: Python :: 3
Classifier: License :: OSI Approved :: MIT License
Classifier: Operating System :: OS Independent
License-File: LICENCE
